apispec_swaggerinherit.py
apispec_swaggerinherit-1.0.1.dist-info/DESCRIPTION.rst
apispec_swaggerinherit-1.0.1.dist-info/METADATA
apispec_swaggerinherit-1.0.1.dist-info/RECORD
apispec_swaggerinherit-1.0.1.dist-info/WHEEL
apispec_swaggerinherit-1.0.1.dist-info/metadata.json
apispec_swaggerinherit-1.0.1.dist-info/top_level.txt
